lsptoolbox/__init__.py
lsptoolbox/common_class.py
lsptoolbox/common_utils.py
lsptoolbox/database_class_define.py
lsptoolbox/database_util.py
lsptoolbox/window_utils.py
lsptoolbox-0.0.9.dist-info/LICENSE
lsptoolbox-0.0.9.dist-info/METADATA
lsptoolbox-0.0.9.dist-info/WHEEL
lsptoolbox-0.0.9.dist-info/top_level.txt
lsptoolbox-0.0.9.dist-info/RECORD
