Metadata-Version: 2.1
Name: lsptoolbox
Version: 0.0.9
Summary: my python project tool box.
Home-page: https://github.com/15608447849/lsp-toolbox
Author: lee bottle
Author-email: 793065165@qq.com
Classifier: Programming Language :: Python :: 3
Classifier: License :: OSI Approved :: MIT License
Classifier: Operating System :: OS Independent
Requires-Python: >=3.6
License-File: LICENSE
